{
  "id": "developer/architecture",
  "title": "Architecture Overview",
  "description": "TLBX-1 is a high-performance, 4-track granular sampler and synthesizer built with Rust, nih-plug, and Slint. It is designed to function as both a standalone application and a professional audio plugin (VST3/CLAP).",
  "source": "@site/docs/developer/architecture.md",
  "sourceDirName": "developer",
  "slug": "/developer/architecture",
  "permalink": "/docs/developer/architecture",
  "draft": false,
  "unlisted": false,
  "tags": [],
  "version": "current",
  "sidebarPosition": 2,
  "frontMatter": {
    "title": "Architecture Overview",
    "sidebar_position": 2
  },
  "sidebar": "devSidebar",
  "previous": {
    "title": "Developer Onboarding",
    "permalink": "/docs/developer/onboarding"
  },
  "next": {
    "title": "Audio Engine",
    "permalink": "/docs/developer/audio-engine"
  }
}